README.md
setup.cfg
setup.py
gdacs_reader/__init__.py
gdacs_reader/exceptions.py
gdacs_reader/gdacs_parser.py
gdacs_reader.egg-info/PKG-INFO
gdacs_reader.egg-info/SOURCES.txt
gdacs_reader.egg-info/dependency_links.txt
gdacs_reader.egg-info/not-zip-safe
gdacs_reader.egg-info/requires.txt
gdacs_reader.egg-info/top_level.txt
tests/__init__.py
tests/test_parser.py