Metadata-Version: 1.1
Name: gdacs-reader
Version: 0.1.1
Summary: An unofficial Python library for fetching updates from the Global Disaster Alert and Coordination System
Home-page: https://github.com/benjiao/gdacs-reader
Author: Benjie Jiao
Author-email: hi@benjie.me
License: BSD
Keywords: GDACS
Platform: any
Classifier: Development Status :: 3 - Alpha
Classifier: Intended Audience :: Developers
Classifier: License :: OSI Approved :: BSD License
Classifier: Operating System :: OS Independent
Classifier: Programming Language :: Python :: 3.6
Classifier: Topic :: Software Development :: Libraries :: Python Modules
